mac.v
module mac(
    input [7:0] a, b,
    output reg [15:0] acc,
    input clk, rst_n
);

    wire [15:0] mul;
    assign mul = a * b;

    always @ (posedge clk) begin
        if (!rst_n) begin
            acc <= 16'd0;
        end
        else begin
            acc <= acc + mul;
        end
    end

endmodule

mac_tb.v
module mactb();
    reg clk, rst_n;
    reg [7:0] a, b;
    wire [15:0] acc;

    mac DUT(
        .clk(clk),
        .rst_n(rst_n),
        .a(a),
        .b(b),
        .acc(acc)
    );

    initial begin
        a = 0;
        b = 0;
    end

    initial begin 
        clk = 1'b0;
        forever #5 clk = ~clk;
    end

    integer i;

    initial begin
        rst_n = 1'b0;
        #15 rst_n = 1'b1;
        for(i = 0; i <= 19; i += 1) begin
            // @(posedge clk)
            @(negedge clk);
            a = i * 2;
            b = i;
        end
    end

    initial begin
        $monitor("Clock = %0t, rst_n = %d, a = %d, b = %d, mul = %d, acc = %d", $time, rst_n, a, b, DUT.mul, acc);
    end

    initial begin
        $dumpfile("mac.vcd");
        $dumpvars(0, DUT);
    end

    initial begin
        #200 $finish;
    end

endmodule

mac.vcd
$date
	Fri May 22 12:22:16 2026
$end
$version
	Icarus Verilog
$end
$timescale
	1s
$end
$scope module mactb $end
$scope module DUT $end
$var wire 8 ! a [7:0] $end
$var wire 8 " b [7:0] $end
$var wire 1 # clk $end
$var wire 1 $ rst_n $end
$var wire 16 % mul [15:0] $end
$var reg 16 & acc [15:0] $end
$upscope $end
$upscope $end
$enddefinitions $end
#0
$dumpvars
bx &
b0 %
0$
0#
b0 "
b0 !
$end
#5
b0 &
1#
#10
0#
#15
1#
1$
#20
0#
#25
1#
#30
b10 %
b1 "
b10 !
0#
#35
b10 &
1#
#40
b10 "
b1000 %
b100 !
0#
#45
b1010 &
1#
#50
b11 "
b10010 %
b110 !
0#
#55
b11100 &
1#
#60
b100 "
b100000 %
b1000 !
0#
#65
b111100 &
1#
#70
b101 "
b110010 %
b1010 !
0#
#75
b1101110 &
1#
#80
b110 "
b1001000 %
b1100 !
0#
#85
b10110110 &
1#
#90
b111 "
b1100010 %
b1110 !
0#
#95
b100011000 &
1#
#100
b1000 "
b10000000 %
b10000 !
0#
#105
b110011000 &
1#
#110
b1001 "
b10100010 %
b10010 !
0#
#115
b1000111010 &
1#
#120
b1010 "
b11001000 %
b10100 !
0#
#125
b1100000010 &
1#
#130
b1011 "
b11110010 %
b10110 !
0#
#135
b1111110100 &
1#
#140
b1100 "
b100100000 %
b11000 !
0#
#145
b10100010100 &
1#
#150
b1101 "
b101010010 %
b11010 !
0#
#155
b11001100110 &
1#
#160
b1110 "
b110001000 %
b11100 !
0#
#165
b11111101110 &
1#
#170
b1111 "
b111000010 %
b11110 !
0#
#175
b100110110000 &
1#
#180
b10000 "
b1000000000 %
b100000 !
0#
#185
b101110110000 &
1#
#190
b10001 "
b1001000010 %
b100010 !
0#
#195
b110111110010 &
1#
#200
b10010 "
b1010001000 %
b100100 !
0#
